importnb/__init__.py
importnb/__main__.py
importnb/_json_parser.py
importnb/_version.py
importnb/decoder.py
importnb/docstrings.py
importnb/entry_points.py
importnb/finder.py
importnb/loader.py
importnb/loaders.py
importnb/utils/__init__.py
importnb/utils/ipython.py
importnb/utils/pytest_importnb.py
importnb-2023.1.7.dist-info/METADATA
importnb-2023.1.7.dist-info/WHEEL
importnb-2023.1.7.dist-info/entry_points.txt
importnb-2023.1.7.dist-info/licenses/LICENSE
importnb-2023.1.7.dist-info/RECORD
