Metadata-Version: 2.1
Name: importnb
Version: 2023.1.7
Summary: import jupyter notebooks as python modules and scripts.
Project-URL: Documentation, https://github.com/deathbeds/importnb#readme
Project-URL: Issues, https://github.com/deathbeds/importnb/issues
Project-URL: Source, https://github.com/deathbeds/importnb
Author-email: tonyfast <tony.fast@gmail.com>
License-Expression: BSD-3-Clause
License-File: LICENSE
Classifier: Development Status :: 4 - Beta
Classifier: Framework :: IPython
Classifier: Framework :: Jupyter
Classifier: License :: OSI Approved :: BSD License
Classifier: Natural Language :: English
Classifier: Programming Language :: Python
Classifier: Programming Language :: Python :: 3.7
Classifier: Programming Language :: Python :: 3.8
Classifier: Programming Language :: Python :: 3.9
Classifier: Programming Language :: Python :: 3.10
Classifier: Programming Language :: Python :: 3.11
Classifier: Programming Language :: Python :: Implementation :: CPython
Classifier: Programming Language :: Python :: Implementation :: PyPy
Requires-Python: >=3.7
Requires-Dist: importlib-metadata; python_version < '3.8'
Provides-Extra: docs
Requires-Dist: mkdocs-jupyter; extra == 'docs'
Requires-Dist: mkdocs-material; extra == 'docs'
Requires-Dist: ruamel-yaml; extra == 'docs'
Provides-Extra: interactive
Requires-Dist: ipython; extra == 'interactive'
Provides-Extra: tasks
Requires-Dist: doit; extra == 'tasks'
Requires-Dist: toml; extra == 'tasks'
